{
  "id": "d411c922-74fb-4281-9332-db6939a7d642",
  "prevId": "00000000-0000-0000-0000-000000000000",
  "version": "7",
  "dialect": "postgresql",
  "tables": {
    "public.contacts": {
      "name": "contacts",
      "schema": "",
      "columns": {
        "id": {
          "name": "id",
          "type": "uuid",
          "primaryKey": true,
          "notNull": true,
          "default": "gen_random_uuid()"
        },
        "name": {
          "name": "name",
          "type": "text",
          "primaryKey": false,
          "notNull": true
        },
        "email": {
          "name": "email",
          "type": "text",
          "primaryKey": false,
          "notNull": true
        },
        "confirmed": {
          "name": "confirmed",
          "type": "boolean",
          "primaryKey": false,
          "notNull": true,
          "default": false
        },
        "confirmed_at": {
          "name": "confirmed_at",
          "type": "timestamp with time zone",
          "primaryKey": false,
          "notNull": false
        },
        "token": {
          "name": "token",
          "type": "uuid",
          "primaryKey": false,
          "notNull": true,
          "default": "gen_random_uuid()"
        },
        "token_expires_at": {
          "name": "token_expires_at",
          "type": "timestamp with time zone",
          "primaryKey": false,
          "notNull": true,
          "default": "now() + interval '48 hours'"
        },
        "created_at": {
          "name": "created_at",
          "type": "timestamp with time zone",
          "primaryKey": false,
          "notNull": true,
          "default": "now()"
        }
      },
      "indexes": {},
      "foreignKeys": {},
      "compositePrimaryKeys": {},
      "uniqueConstraints": {
        "contacts_email_unique": {
          "name": "contacts_email_unique",
          "nullsNotDistinct": false,
          "columns": [
            "email"
          ]
        },
        "contacts_token_unique": {
          "name": "contacts_token_unique",
          "nullsNotDistinct": false,
          "columns": [
            "token"
          ]
        }
      },
      "policies": {},
      "checkConstraints": {},
      "isRLSEnabled": false
    }
  },
  "enums": {},
  "schemas": {},
  "sequences": {},
  "roles": {},
  "policies": {},
  "views": {},
  "_meta": {
    "columns": {},
    "schemas": {},
    "tables": {}
  }
}